CHANGES.rst
LICENSE
MANIFEST.in
README.rst
run.py
setup.py
conf/90-usb-microbit.rules
conf/mu.appdata.xml
conf/mu.codewith.editor.desktop
conf/mu.codewith.editor.png
mu/__init__.py
mu/__main__.py
mu/app.py
mu/logic.py
mu/mu-debug.py
mu/contrib/__init__.py
mu/contrib/microfs.py
mu/contrib/uflash.py
mu/debugger/client.py
mu/debugger/runner.py
mu/debugger/utils.py
mu/interface/__init__.py
mu/interface/dialogs.py
mu/interface/editor.py
mu/interface/main.py
mu/interface/panes.py
mu/interface/themes.py
mu/locale/de_DE/LC_MESSAGES/mu.mo
mu/locale/de_DE/LC_MESSAGES/mu.po
mu/locale/es/LC_MESSAGES/mu.mo
mu/locale/es/LC_MESSAGES/mu.po
mu/locale/fr/LC_MESSAGES/mu.mo
mu/locale/fr/LC_MESSAGES/mu.po
mu/locale/ja/LC_MESSAGES/mu.mo
mu/locale/ja/LC_MESSAGES/mu.po
mu/locale/pl/LC_MESSAGES/mu.mo
mu/locale/pl/LC_MESSAGES/mu.po
mu/locale/pt_BR/LC_MESSAGES/mu.mo
mu/locale/pt_BR/LC_MESSAGES/mu.po
mu/locale/pt_PT/LC_MESSAGES/mu.mo
mu/locale/pt_PT/LC_MESSAGES/mu.po
mu/locale/sv/LC_MESSAGES/mu.mo
mu/locale/sv/LC_MESSAGES/mu.po
mu/locale/vi/LC_MESSAGES/mu.mo
mu/locale/vi/LC_MESSAGES/mu.po
mu/locale/zh_CN/LC_MESSAGES/mu.mo
mu/locale/zh_CN/LC_MESSAGES/mu.po
mu/modes/__init__.py
mu/modes/adafruit.py
mu/modes/base.py
mu/modes/debugger.py
mu/modes/esp.py
mu/modes/microbit.py
mu/modes/pygamezero.py
mu/modes/python3.py
mu/modes/api/__init__.py
mu/modes/api/adafruit.py
mu/modes/api/esp.py
mu/modes/api/microbit.py
mu/modes/api/pi.py
mu/modes/api/pygamezero.py
mu/modes/api/python3.py
mu/modes/api/shared.py
mu/resources/__init__.py
mu/resources/css/contrast.css
mu/resources/css/day.css
mu/resources/css/night.css
mu/resources/fonts/LICENSE.txt
mu/resources/fonts/SourceCodePro-Bold.otf
mu/resources/fonts/SourceCodePro-BoldIt.otf
mu/resources/fonts/SourceCodePro-It.otf
mu/resources/fonts/SourceCodePro-Regular.otf
mu/resources/fonts/SourceCodePro-Semibold.otf
mu/resources/fonts/SourceCodePro-SemiboldIt.otf
mu/resources/images/adafruit.png
mu/resources/images/button.png
mu/resources/images/check.png
mu_sb.egg-info/PKG-INFO
mu_sb.egg-info/SOURCES.txt
mu_sb.egg-info/dependency_links.txt
mu_sb.egg-info/entry_points.txt
mu_sb.egg-info/not-zip-safe
mu_sb.egg-info/requires.txt
mu_sb.egg-info/top_level.txt